digitalocean_access_spaces/__init__.py
digitalocean_access_spaces/digitalocean_access_spaces.py
digitalocean_access_spaces-1.2.dist-info/METADATA
digitalocean_access_spaces-1.2.dist-info/WHEEL
digitalocean_access_spaces-1.2.dist-info/top_level.txt
digitalocean_access_spaces-1.2.dist-info/RECORD
